{
  "analysis_timestamp": "2026-02-13T03:02:12Z",
  "app_name": "vector-frogger-logs-and-turtles",
  "overall_status": "PASSED",
  "summary": "All static analysis checks passed. The project is well-structured and ready to build and run.",
  "checks": {
    "project_structure": {
      "status": "PASSED",
      "description": "Project structure is valid",
      "details": {
        "expected_files": {
          "main.py": "PRESENT",
          "game.py": "PRESENT",
          "entities.py": "PRESENT",
          "config.py": "PRESENT",
          "pyproject.toml": "PRESENT",
          "appinfo.json": "PRESENT"
        },
        "all_required_files_present": true
      }
    },
    "python_syntax": {
      "status": "PASSED",
      "description": "All Python files have valid syntax",
      "files_checked": [
        "main.py - PASSED",
        "game.py - PASSED",
        "entities.py - PASSED",
        "config.py - PASSED"
      ]
    },
    "imports": {
      "status": "PASSED",
      "description": "All imports are valid and resolvable",
      "modules_imported": [
        {
          "module": "pygame",
          "status": "INSTALLED",
          "version": "2.5.6 (pygame-ce)",
          "note": "pygame-ce is the community edition of pygame, compatible with standard pygame API"
        }
      ],
      "local_imports": [
        "main.py imports: pygame, game.Game",
        "game.py imports: pygame, config.*, entities.Frog, entities.Lane",
        "entities.py imports: pygame, config.*"
      ],
      "circular_dependencies": "NONE_DETECTED"
    },
    "code_quality": {
      "status": "PASSED",
      "description": "Code follows Python best practices",
      "findings": [
        {
          "category": "Module Organization",
          "status": "GOOD",
          "details": "Clean separation of concerns: config, entities, game logic, and entry point"
        },
        {
          "category": "Naming Conventions",
          "status": "GOOD",
          "details": "PEP 8 compliant class names (PascalCase) and function/variable names (snake_case)"
        },
        {
          "category": "Documentation",
          "status": "GOOD",
          "details": "All classes and methods have docstrings"
        }
      ]
    },
    "configuration": {
      "status": "PASSED",
      "description": "Project configuration is valid",
      "pyproject.toml": {
        "name": "vector-frogger-logs-and-turtles",
        "version": "1.0.0",
        "requires_python": ">=3.12",
        "dependencies": ["pygame-ce>=2.5.0"],
        "entry_point": "main:main",
        "valid": true
      },
      "appinfo.json": {
        "valid_json": true,
        "required_fields_present": true,
        "technical_specs_match_code": true
      }
    },
    "dependencies": {
      "status": "PASSED",
      "description": "All dependencies are properly specified and available",
      "dependencies_list": [
        {
          "name": "pygame-ce",
          "version_spec": ">=2.5.0",
          "installed_version": "2.5.6",
          "compatible": true
        }
      ]
    },
    "build_readiness": {
      "status": "PASSED",
      "description": "Project is ready to build",
      "assessed_criteria": [
        {
          "criterion": "Entry Point",
          "status": "PRESENT",
          "details": "main.py contains main() function that initializes pygame and starts the game loop"
        },
        {
          "criterion": "Virtual Environment",
          "status": "PRESENT",
          "details": ".venv directory exists with pygame-ce installed"
        },
        {
          "criterion": "Build System",
          "status": "CONFIGURED",
          "details": "Uses hatchling as build backend, specified in pyproject.toml"
        }
      ]
    },
    "runtime_readiness": {
      "status": "PASSED",
      "description": "Project is ready to run",
      "expected_behavior": [
        "1. pygame.init() initializes the pygame library",
        "2. Game class creates display window (600x600)",
        "3. Main game loop runs at 60 FPS",
        "4. Keyboard input handled (UP, DOWN, LEFT, RIGHT arrows, ESC, SPACE)",
        "5. Game entities (Frog, Log, Turtle, Lane) properly initialized"
      ],
      "potential_issues": []
    },
    "game_logic_validation": {
      "status": "PASSED",
      "description": "Game logic matches appinfo.json specifications",
      "specifications_checked": [
        {
          "spec": "Grid Size",
          "expected": "10x10",
          "actual": "10x10 (COLS=10, ROWS=10)",
          "match": true
        },
        {
          "spec": "Frog Entity",
          "expected": "Green color, Player type",
          "actual": "COLOR_FROG = (60, 220, 60), Frog class present",
          "match": true
        },
        {
          "spec": "Log Entity",
          "expected": "Brown color, Stable behavior",
          "actual": "COLOR_LOG = (130, 90, 50), Log class with stable movement",
          "match": true
        },
        {
          "spec": "Turtle Entity",
          "expected": "Red color, Submerges every 3 seconds",
          "actual": "COLOR_TURTLE = (200, 70, 60), TURTLE_SUBMERGE_CYCLE = 3000ms",
          "match": true
        },
        {
          "spec": "Win Condition",
          "expected": "Reach top row",
          "actual": "if self.frog.grid_y == GOAL_ROW (row 0)",
          "match": true
        },
        {
          "spec": "Lose Condition",
          "expected": "Touch water or move off-screen",
          "actual": "Water collision check in _check_river_collision(), bounds check in update()",
          "match": true
        },
        {
          "spec": "Scoring",
          "expected": "+10 forward, +100 goal, -50 death, -1 time",
          "actual": "SCORE_FORWARD=10, SCORE_GOAL=100, DEATH_PENALTY=-50, TIME_PENALTY=-1",
          "match": true
        }
      ]
    },
    "platform_compatibility": {
      "status": "PASSED",
      "description": "Code is cross-platform compatible",
      "details": "Uses pygame for rendering which works on Windows, macOS, and Linux. No platform-specific code detected."
    }
  },
  "recommendations": [],
  "warnings": [
    {
      "severity": "INFO",
      "category": "Documentation",
      "message": "The project uses pygame-ce (Community Edition) which imports as 'pygame', not 'pygame_ce'. This is correct as pygame-ce is a drop-in replacement for standard pygame."
    }
  ],
  "verification_steps": [
    "1. Run: uv run main.py (or python main.py if using system Python)",
    "2. Verify window opens with 600x600 resolution",
    "3. Verify frog appears in starting position (bottom row)",
    "4. Test arrow keys for movement",
    "5. Verify collision detection with water, logs, and turtles",
    "6. Verify turtle submersion behavior (3 second cycle)"
  ]
}
